tiedpyranges/__init__.py
tiedpyranges/tiedpyranges.py
tiedpyranges-0.1.3.dist-info/LICENSE
tiedpyranges-0.1.3.dist-info/METADATA
tiedpyranges-0.1.3.dist-info/WHEEL
tiedpyranges-0.1.3.dist-info/top_level.txt
tiedpyranges-0.1.3.dist-info/RECORD
