Metadata-Version: 2.1
Name: tiedpyranges
Version: 0.1.3
Summary: Extends the pyranges module with operations on joined genomic intervals (e.g. exons of same transcript)
Home-page: https://github.com/marco-mariotti/tiedpyranges
Author: Marco Mariotti
Author-email: marco.mariotti.mm@gmail.com
License: UNKNOWN
Platform: UNKNOWN
Classifier: Programming Language :: Python :: 3
Classifier: License :: OSI Approved :: MIT License
Classifier: Operating System :: OS Independent
License-File: LICENSE
Requires-Dist: pandas (>=1.2)
Requires-Dist: pyranges (>=0.0.99)
Requires-Dist: pyfaidx (>=0.6)
